docutils-stubs/__init__.pyi
docutils-stubs/_compat.pyi
docutils-stubs/core.pyi
docutils-stubs/examples.pyi
docutils-stubs/frontend.pyi
docutils-stubs/io.pyi
docutils-stubs/nodes.pyi
docutils-stubs/statemachine.pyi
docutils-stubs/languages/__init__.pyi
docutils-stubs/languages/af.pyi
docutils-stubs/languages/ca.pyi
docutils-stubs/languages/cs.pyi
docutils-stubs/languages/da.pyi
docutils-stubs/languages/de.pyi
docutils-stubs/languages/en.pyi
docutils-stubs/languages/eo.pyi
docutils-stubs/languages/es.pyi
docutils-stubs/languages/fa.pyi
docutils-stubs/languages/fi.pyi
docutils-stubs/languages/fr.pyi
docutils-stubs/languages/gl.pyi
docutils-stubs/languages/he.pyi
docutils-stubs/languages/it.pyi
docutils-stubs/languages/ja.pyi
docutils-stubs/languages/ko.pyi
docutils-stubs/languages/lt.pyi
docutils-stubs/languages/lv.pyi
docutils-stubs/languages/nl.pyi
docutils-stubs/languages/pl.pyi
docutils-stubs/languages/pt_br.pyi
docutils-stubs/languages/ru.pyi
docutils-stubs/languages/sk.pyi
docutils-stubs/languages/sv.pyi
docutils-stubs/languages/zh_cn.pyi
docutils-stubs/languages/zh_tw.pyi
docutils-stubs/parsers/__init__.pyi
docutils-stubs/parsers/null.pyi
docutils-stubs/parsers/rst/__init__.pyi
docutils-stubs/parsers/rst/roles.pyi
docutils-stubs/parsers/rst/states.pyi
docutils-stubs/parsers/rst/tableparser.pyi
docutils-stubs/parsers/rst/directives/__init__.pyi
docutils-stubs/parsers/rst/directives/admonitions.pyi
docutils-stubs/parsers/rst/directives/body.pyi
docutils-stubs/parsers/rst/directives/html.pyi
docutils-stubs/parsers/rst/directives/images.pyi
docutils-stubs/parsers/rst/directives/misc.pyi
docutils-stubs/parsers/rst/directives/parts.pyi
docutils-stubs/parsers/rst/directives/references.pyi
docutils-stubs/parsers/rst/directives/tables.pyi
docutils-stubs/parsers/rst/languages/__init__.pyi
docutils-stubs/parsers/rst/languages/af.pyi
docutils-stubs/parsers/rst/languages/ca.pyi
docutils-stubs/parsers/rst/languages/cs.pyi
docutils-stubs/parsers/rst/languages/da.pyi
docutils_stubs-0.0.22.dist-info/LICENSE
docutils_stubs-0.0.22.dist-info/METADATA
docutils_stubs-0.0.22.dist-info/WHEEL
docutils_stubs-0.0.22.dist-info/top_level.txt
docutils_stubs-0.0.22.dist-info/RECORD
