Metadata-Version: 2.1
Name: docutils-stubs
Version: 0.0.22
Summary: PEP 561 type stubs for docutils
Home-page: https://github.com/tk0miya/docutils-stubs
Author: Takeshi KOMIYA, cocoatomo
Author-email: i.tkomiya@gmail.com, cocoatomo77@gmail.com
License: Unlicense
Platform: UNKNOWN
Classifier: License :: OSI Approved :: The Unlicense (Unlicense)
Requires-Python: >=3.5
License-File: LICENSE
Requires-Dist: docutils (>=0.14)
